[{
		"name":	"Jonas",
		"year":	1990,
		"dayMonth":	1.01
	}, {
		"name":	"Petras",
		"year":	1991,
		"dayMonth":	2.02
	}, {
		"name":	"Antanas",
		"year":	1992,
		"dayMonth":	3.03
	}, {
		"name":	"Juozas",
		"year":	1993,
		"dayMonth":	4.04
	}, {
		"name":	"Stasys",
		"year":	1994,
		"dayMonth":	5.05
	}, {
		"name":	"Jonas",
		"year":	1995,
		"dayMonth":	6.06
	}, {
		"name":	"Petras",
		"year":	1996,
		"dayMonth":	7.07
	}, {
		"name":	"Antanas",
		"year":	1997,
		"dayMonth":	8.08
	}, {
		"name":	"Juozas",
		"year":	1998,
		"dayMonth":	9.09
	}, {
		"name":	"Stasys",
		"year":	1999,
		"dayMonth":	10.1
	}, {
		"name":	"Jonas",
		"year":	2000,
		"dayMonth":	11.11
	}, {
		"name":	"Petras",
		"year":	2001,
		"dayMonth":	12.12
	}, {
		"name":	"Antanas",
		"year":	2002,
		"dayMonth":	13.01
	}, {
		"name":	"Juozas",
		"year":	2003,
		"dayMonth":	14.02
	}, {
		"name":	"Stasys",
		"year":	2004,
		"dayMonth":	15.03
	}, {
		"name":	"Jonas",
		"year":	2005,
		"dayMonth":	16.04
	}, {
		"name":	"Petras",
		"year":	2006,
		"dayMonth":	17.05
	}, {
		"name":	"Antanas",
		"year":	2007,
		"dayMonth":	18.06
	}, {
		"name":	"Juozas",
		"year":	2008,
		"dayMonth":	19.07
	}, {
		"name":	"Stasys",
		"year":	2009,
		"dayMonth":	20.08
	}, {
		"name":	"Jonas",
		"year":	2010,
		"dayMonth":	21.09
	}, {
		"name":	"Petras",
		"year":	2011,
		"dayMonth":	22.1
	}, {
		"name":	"Antanas",
		"year":	2012,
		"dayMonth":	23.11
	}, {
		"name":	"Juozas",
		"year":	2013,
		"dayMonth":	24.12
	}, {
		"name":	"Stasys",
		"year":	2014,
		"dayMonth":	25.01
	}, {
		"name":	"Jonas",
		"year":	2015,
		"dayMonth":	26.02
	}, {
		"name":	"Petras",
		"year":	2016,
		"dayMonth":	27.03
	}, {
		"name":	"Antanas",
		"year":	2017,
		"dayMonth":	28.04
	}, {
		"name":	"Juozas",
		"year":	2018,
		"dayMonth":	29.05
	}, {
		"name":	"Stasys",
		"year":	2019,
		"dayMonth":	30.06
	}, {
		"name":	"Jonas",
		"year":	1990,
		"dayMonth":	31.07
	}, {
		"name":	"Petras",
		"year":	1991,
		"dayMonth":	1.08
	}, {
		"name":	"Antanas",
		"year":	1992,
		"dayMonth":	2.09
	}, {
		"name":	"Juozas",
		"year":	1993,
		"dayMonth":	3.1
	}, {
		"name":	"Stasys",
		"year":	1994,
		"dayMonth":	4.11
	}, {
		"name":	"Jonas",
		"year":	1995,
		"dayMonth":	5.12
	}, {
		"name":	"Petras",
		"year":	1996,
		"dayMonth":	6.01
	}, {
		"name":	"Antanas",
		"year":	1997,
		"dayMonth":	7.02
	}, {
		"name":	"Juozas",
		"year":	1998,
		"dayMonth":	8.03
	}, {
		"name":	"Stasys",
		"year":	1999,
		"dayMonth":	9.04
	}, {
		"name":	"Jonas",
		"year":	2000,
		"dayMonth":	10.05
	}, {
		"name":	"Petras",
		"year":	2001,
		"dayMonth":	11.06
	}, {
		"name":	"Antanas",
		"year":	2002,
		"dayMonth":	12.07
	}, {
		"name":	"Juozas",
		"year":	2003,
		"dayMonth":	13.08
	}, {
		"name":	"Stasys",
		"year":	2004,
		"dayMonth":	14.09
	}, {
		"name":	"Jonas",
		"year":	2005,
		"dayMonth":	15.1
	}, {
		"name":	"Petras",
		"year":	2006,
		"dayMonth":	16.11
	}, {
		"name":	"Antanas",
		"year":	2007,
		"dayMonth":	17.12
	}, {
		"name":	"Juozas",
		"year":	2008,
		"dayMonth":	18.01
	}, {
		"name":	"Stasys",
		"year":	2009,
		"dayMonth":	19.02
	}, {
		"name":	"Jonas",
		"year":	2010,
		"dayMonth":	20.03
	}, {
		"name":	"Petras",
		"year":	2011,
		"dayMonth":	21.04
	}, {
		"name":	"Antanas",
		"year":	2012,
		"dayMonth":	22.05
	}, {
		"name":	"Juozas",
		"year":	2013,
		"dayMonth":	23.06
	}, {
		"name":	"Stasys",
		"year":	2014,
		"dayMonth":	24.07
	}, {
		"name":	"Jonas",
		"year":	2015,
		"dayMonth":	25.08
	}, {
		"name":	"Petras",
		"year":	2016,
		"dayMonth":	26.09
	}, {
		"name":	"Antanas",
		"year":	2017,
		"dayMonth":	27.1
	}, {
		"name":	"Juozas",
		"year":	2018,
		"dayMonth":	28.11
	}, {
		"name":	"Stasys",
		"year":	2019,
		"dayMonth":	29.12
	}, {
		"name":	"Jonas",
		"year":	1990,
		"dayMonth":	30.01
	}, {
		"name":	"Petras",
		"year":	1991,
		"dayMonth":	31.02
	}, {
		"name":	"Antanas",
		"year":	1992,
		"dayMonth":	1.03
	}, {
		"name":	"Juozas",
		"year":	1993,
		"dayMonth":	2.04
	}, {
		"name":	"Stasys",
		"year":	1994,
		"dayMonth":	3.05
	}, {
		"name":	"Jonas",
		"year":	1995,
		"dayMonth":	4.06
	}, {
		"name":	"Petras",
		"year":	1996,
		"dayMonth":	5.07
	}, {
		"name":	"Antanas",
		"year":	1997,
		"dayMonth":	6.08
	}, {
		"name":	"Juozas",
		"year":	1998,
		"dayMonth":	7.09
	}, {
		"name":	"Stasys",
		"year":	1999,
		"dayMonth":	8.1
	}, {
		"name":	"Jonas",
		"year":	2000,
		"dayMonth":	9.11
	}, {
		"name":	"Petras",
		"year":	2001,
		"dayMonth":	10.12
	}, {
		"name":	"Antanas",
		"year":	2002,
		"dayMonth":	11.01
	}, {
		"name":	"Juozas",
		"year":	2003,
		"dayMonth":	12.02
	}, {
		"name":	"Stasys",
		"year":	2004,
		"dayMonth":	13.03
	}, {
		"name":	"Jonas",
		"year":	2005,
		"dayMonth":	14.04
	}, {
		"name":	"Petras",
		"year":	2006,
		"dayMonth":	15.05
	}, {
		"name":	"Antanas",
		"year":	2007,
		"dayMonth":	16.06
	}, {
		"name":	"Juozas",
		"year":	2008,
		"dayMonth":	17.07
	}, {
		"name":	"Stasys",
		"year":	2009,
		"dayMonth":	18.08
	}, {
		"name":	"Jonas",
		"year":	2010,
		"dayMonth":	19.09
	}, {
		"name":	"Petras",
		"year":	2011,
		"dayMonth":	20.1
	}, {
		"name":	"Antanas",
		"year":	2012,
		"dayMonth":	21.11
	}, {
		"name":	"Juozas",
		"year":	2013,
		"dayMonth":	22.12
	}, {
		"name":	"Stasys",
		"year":	2014,
		"dayMonth":	23.01
	}, {
		"name":	"Jonas",
		"year":	2015,
		"dayMonth":	24.02
	}, {
		"name":	"Petras",
		"year":	2016,
		"dayMonth":	25.03
	}, {
		"name":	"Antanas",
		"year":	2017,
		"dayMonth":	26.04
	}, {
		"name":	"Juozas",
		"year":	2018,
		"dayMonth":	27.05
	}, {
		"name":	"Stasys",
		"year":	2019,
		"dayMonth":	28.06
	}, {
		"name":	"Jonas",
		"year":	1990,
		"dayMonth":	29.07
	}, {
		"name":	"Petras",
		"year":	1991,
		"dayMonth":	30.08
	}, {
		"name":	"Antanas",
		"year":	1992,
		"dayMonth":	31.09
	}, {
		"name":	"Juozas",
		"year":	1993,
		"dayMonth":	1.1
	}, {
		"name":	"Stasys",
		"year":	1994,
		"dayMonth":	2.11
	}, {
		"name":	"Jonas",
		"year":	1995,
		"dayMonth":	3.12
	}, {
		"name":	"Petras",
		"year":	1996,
		"dayMonth":	4.01
	}, {
		"name":	"Antanas",
		"year":	1997,
		"dayMonth":	5.02
	}, {
		"name":	"Juozas",
		"year":	1998,
		"dayMonth":	6.03
	}, {
		"name":	"Stasys",
		"year":	1999,
		"dayMonth":	7.04
	}]